{
  "last_updated": "2026-06-20 09:55:03 UTC",
  "period_start": "2026-05-21",
  "period_end": "2026-06-19",
  "total_revenue": 65.23,
  "cpm": 7.21,
  "monetized_playbacks": 7077,
  "ad_impressions": 14478,
  "total_views": 16005,
  "rpm": 4.08,
  "revenue_change": -35.4,
  "rpm_change": 52.1,
  "cpm_change": 15.9,
  "playbacks_change": -53.3,
  "revenue_chart": {
    "labels": [
      "May 21",
      "May 22",
      "May 23",
      "May 24",
      "May 25",
      "May 26",
      "May 27",
      "May 28",
      "May 29",
      "May 30",
      "May 31",
      "Jun 01",
      "Jun 02",
      "Jun 03",
      "Jun 04",
      "Jun 05",
      "Jun 06",
      "Jun 07",
      "Jun 08",
      "Jun 09",
      "Jun 10",
      "Jun 11",
      "Jun 12",
      "Jun 13",
      "Jun 14",
      "Jun 15",
      "Jun 16",
      "Jun 17"
    ],
    "values": [
      8.19,
      5.01,
      3.09,
      3.4,
      2.05,
      2.12,
      2.46,
      3.5,
      1.91,
      2.18,
      1.28,
      1.49,
      1.62,
      1.6,
      2.62,
      2.36,
      1.43,
      1.64,
      1.38,
      1.46,
      0.94,
      3.39,
      2.26,
      1.97,
      2.06,
      1.33,
      1.24,
      1.27
    ]
  },
  "ad_type_breakdown": {},
  "top_earning_videos": [
    {
      "title": "Hands All Over the Icom ID-5200! | Hamvention 2026",
      "revenue": 6.29,
      "views": 2366,
      "video_id": "LIM0hjXez1Q"
    },
    {
      "title": "Icom's \"Concept Car\" - The X-026 with Ray Novak N9JA | Hamvention 2026",
      "revenue": 5.66,
      "views": 1747,
      "video_id": "IEwwzO5Uf6Q"
    },
    {
      "title": "It's REAL and It Works! Kenwood TM-D750A First Powered-On Look | Hamvention 2026",
      "revenue": 5.35,
      "views": 1584,
      "video_id": "ZYk8IUSeEHI"
    },
    {
      "title": "Learning CW in 2026: Two Paths to Morse Code Success",
      "revenue": 5.3,
      "views": 557,
      "video_id": "cGQR0gc20OY"
    },
    {
      "title": "Hamvention 2026 Haul Showdown: Whose Bag Was Best?",
      "revenue": 3.92,
      "views": 457,
      "video_id": "fZkumHnnbGI"
    }
  ],
  "projected_monthly_revenue": 65.23
}